Workbook

Sheet Finl Stmts
A1: The Boston Beer Company Inc Balance Sheet As of December 31 2023 | I1: The Boston Beer Company Inc Comparative Balance Sheet As of December 31 2023 | L1: The Boston Beer Company Inc Common Sized Balance Sheet As of December 31 2023 | P1: Boston Beer Company Inc Trend Analysis Balance Sheet (% of Base yr ) As of December 31 2023
B4: 2023 | D4: =B4-1 -> 2022 | F4: =D4-1 -> 2021 | I4: =B4 -> 2023 | J4: =D4 -> 2022 | L4: =B4 -> 2023 | M4: =D4 -> 2022 | N4: =F4 -> 2021 | P4: =B4 -> 2023
A5: Current Assets: | F5: Base Year
A6: Cash & Cash Equivalents (= Stmt of CF ending Cash Balance) | B6: 298491 | D6: 180560 | F6: 26853 | I6: =(B6-D6)/D6 -> 0.65314023 | J6: =(D6-F6)/F6 -> 5.7240159 | L6: =B6/$B$20 -> 0.20873599 | M6: =D6/$D$20 -> 0.12708575 | N6: =F6/$F$20 -> 0.019363506 | P6: =(B6-$F6)/$F6 -> 10.115741
A7: Marketable Securities / Investments/ Restricted Cash | F7: 39468 | I7: =IFERROR((B7-D7)/D7,0) -> 0 | J7: =(D7-F7)/F7 -> -1 | L7: =B7/$B$20 -> 0 | M7: =D7/$D$20 -> 0 | N7: =F7/$F$20 -> 0.028460092 | P7: =(B7-$F7)/$F7 -> -1
A8: Accounts Receivable, net | B8: 66997 | D8: 56672 | F8: 55022 | I8: =(B8-D8)/D8 -> 0.18218874 | J8: =(D8-F8)/F8 -> 0.029988005 | L8: =B8/$B$20 -> 0.046851278 | M8: =D8/$D$20 -> 0.039888145 | N8: =F8/$F$20 -> 0.03967597 | P8: =(B8-$F8)/$F8 -> 0.21764022
A9: Inventories | B9: 115773 | D9: 148450 | F9: 149118 | I9: =(B9-D9)/D9 -> -0.22012125 | J9: =(D9-F9)/F9 -> -0.0044796738 | L9: =B9/$B$20 -> 0.080960536 | M9: =D9/$D$20 -> 0.10448538 | N9: =F9/$F$20 -> 0.10752792 | P9: =(B9-$F9)/$F9 -> -0.22361486
A10: Prepaid expenses & Other Current Assest & Deferred Income Taxes Receivable | B10: =20538+1711 -> 22249 | D10: =27461+10126 -> 37587 | F10: =21462+53418 -> 74880 | I10: =(B10-D10)/D10 -> -0.40806662 | J10: =(D10-F10)/F10 -> -0.49803686 | L10: =B10/$B$20 -> 0.015558817 | M10: =D10/D20 -> 0.026455317 | N10: =F10/F20 -> 0.053995431 | P10: =(B10-$F10)/$F10 -> -0.70287126 | R10: Do not analyze this account
A11: Total current assets | B11: =SUM(B6:B10) -> 503510 | D11: =SUM(D6:D10) -> 423269 | F11: =SUM(F6:F10) -> 345341 | I11: =(B11-D11)/D11 -> 0.18957448 | J11: =(D11-F11)/F11 -> 0.22565522 | L11: =B11/$B$20 -> 0.35210662 | M11: =D11/$D$20 -> 0.29791459 | N11: =F11/$F$20 -> 0.24902292 | P11: =(B11-$F11)/$F11 -> 0.45800817
A12: Non-Current Assets:
A13: Net Property, Plant & Equipment ( Fixed Assets) | B13: 642509 | D13: 667909 | F13: 664815 | I13: =(B13-D13)/D13 -> -0.038029133 | J13: =(D13-F13)/F13 -> 0.0046539263 | L13: =B13/$B$20 -> 0.44930919 | M13: =D13/$D$20 -> 0.47010254 | N13: =F13/$F$20 -> 0.47939333 | P13: =(B13-$F13)/$F13 -> -0.033552191
A14: Operating Right-of-use Assests | B14: 35559 | D14: 43768 | F14: 52774 | I14: =(B14-D14)/D14 -> -0.18755712 | J14: =(D14-F14)/F14 -> -0.17065222 | L14: =B14/$B$20 -> 0.024866555 | M14: =D14/$D$20 -> 0.030805766 | N14: =F14/$F$20 -> 0.038054953 | P14: =(B14-$F14)/$F14 -> -0.3262023
A15: Goodwill | B15: 112529 | D15: 112529 | F15: 112529 | I15: =(B15-D15)/D15 -> 0 | J15: =(D15-F15)/F15 -> 0 | L15: =B15/$B$20 -> 0.078691994 | M15: =D15/$D$20 -> 0.079202659 | N15: =F15/$F$20 -> 0.081143855 | P15: =(B15-$F15)/$F15 -> 0
A16: Marketable Securities/Investments (long-term) | B16: 0 | D16: 0 | F16: 0 | I16: =IFERROR((B16-D16)/D16,0) -> 0 | J16: =IFERROR((D16-F16)/F16,0) -> 0 | L16: =B16/B20 -> 0 | M16: =D16/$D$20 -> 0 | N16: =F16/$F$20 -> 0 | P16: =IFERROR((B16-$F16)/$F16,0) -> 0
A17: Other intangibles | B17: 59644 | D17: 76324 | F17: 103677 | I17: =(B17-D17)/D17 -> -0.21854201 | J17: =(D17-F17)/F17 -> -0.26382901 | L17: =B17/B20 -> 0.041709295 | M17: =D17/$D$20 -> 0.053720052 | N17: =F17/$F$20 -> 0.074760741 | P17: =(B17-$F17)/$F17 -> -0.42471329
A18: Third-party production prepayments | B18: 33581 | D18: 61339 | F18: 88294 | I18: =(B18-D18)/D18 -> -0.45253428 | J18: =(D18-F18)/F18 -> -0.30528688 | L18: =B18/B20 -> 0.023483332 | M18: =D18/$D$20 -> 0.043172977 | N18: =F18/$F$20 -> 0.06366817 | P18: =(B18-$F18)/$F18 -> -0.61966838 | R18: Do not analyze this account
A19: Other Long Term Assets | B19: 42661 | D19: 35635 | F19: 19354 | I19: =(B19-D19)/D19 -> 0.19716571 | J19: =(D19-F19)/F19 -> 0.84122145 | L19: =B19/$B$20 -> 0.029833013 | M19: =D19/$D$20 -> 0.025081417 | N19: =F19/$F$20 -> 0.013956031 | P19: =(B19-$F19)/$F19 -> 1.2042472
A20: TOTAL ASSETS | B20: =SUM(B11:B19) -> 1429993 | D20: =SUM(D11:D19) -> 1420773 | F20: =SUM(F11:F19) -> 1386784 | I20: =(B20-D20)/D20 -> 0.0064894251 | J20: =(D20-F20)/F20 -> 0.024509224 | L20: =SUM(L11:L19) -> 1 | M20: =SUM(M11:M19) -> 1 | N20: =SUM(N11:N19) -> 1 | P20: =(B20-$F20)/$F20 -> 0.0311577
L21: should = 100% | M21: should = 100% | N21: should = 100%
A22: Current Liabilities:
A23: Accounts Payable | B23: 87245 | D23: 84248 | F23: 85920 | I23: =(B23-D23)/D23 -> 0.035573545 | J23: =(D23-F23)/F23 -> -0.019459963 | L23: =B23/$B$20 -> 0.061010788 | M23: =D23/$D$20 -> 0.059297298 | N23: =F23/$F$20 -> 0.061956296 | P23: =(B23-$F23)/$F23 -> 0.015421322
A24: Accrued liabilities | B24: 126930 | D24: 111153 | F24: 161552 | I24: =(B24-D24)/D24 -> 0.14193949 | J24: =(D24-F24)/F24 -> -0.31196766 | L24: =B24/$B$20 -> 0.088762672 | M24: =D24/$D$20 -> 0.078234173 | N24: =F24/$F$20 -> 0.11649399 | P24: =(B24-$F24)/$F24 -> -0.21430871
A25: Deferred Revenue (Unearned revenue) | I25: =(B25-D25)/D25 -> #DIV/0! | J25: =(D25-F25)/F25 -> #DIV/0! | L25: =B25/$B$20 -> 0 | M25: =D25/$D$20 -> 0 | N25: =F25/$F$20 -> 0 | P25: =(B25-$F25)/$F25 -> #DIV/0!
A26: Deferred Income Taxes | I26: =(B26-D26)/D26 -> #DIV/0! | J26: =(D26-F26)/F26 -> #DIV/0! | L26: =B26/$B$20 -> 0 | M26: =D26/$D$20 -> 0 | N26: =F26/$F$20 -> 0 | P26: =(B26-$F26)/$F26 -> #DIV/0! | R26: Do not analyze this account
A27: Other liabilities | I27: =(B27-D27)/D27 -> #DIV/0! | J27: =(D27-F27)/F27 -> #DIV/0! | L27: =B27/$B$20 -> 0 | M27: =D27/$D$20 -> 0 | N27: =F27/$F$20 -> 0 | P27: =(B27-$F27)/$F27 -> #DIV/0!
A28: Current portion of Long Term debt (interest bearing debt) + Leases | B28: 9113 | D28: 8866 | F28: 7634 | I28: =(B28-D28)/D28 -> 0.027859238 | J28: =(D28-F28)/F28 -> 0.16138329 | L28: =B28/$B$20 -> 0.0063727585 | M28: =D28/$D$20 -> 0.006240265 | N28: =F28/$F$20 -> 0.0055048227 | P28: =(B28-$F28)/$F28 -> 0.19373854
A29: Total current liabilities | B29: =SUM(B22:B28) -> 223288 | D29: =SUM(D22:D28) -> 204267 | F29: =SUM(F22:F28) -> 255106 | I29: =(B29-D29)/D29 -> 0.093118321 | J29: =(D29-F29)/F29 -> -0.19928579 | L29: =B29/$B$20 -> 0.15614622 | M29: =D29/$D$20 -> 0.14377174 | N29: =F29/$F$20 -> 0.18395511 | P29: =(B29-$F29)/$F29 -> -0.12472462
A30: Deferred Income Taxes - LT | B30: 85721 | D30: 96592 | F30: 87495 | I30: =(B30-D30)/D30 -> -0.11254555 | J30: =(D30-F30)/F30 -> 0.10397166 | L30: =B30/$B$20 -> 0.059945049 | M30: =D30/$D$20 -> 0.067985526 | N30: =F30/$F$20 -> 0.063092017 | P30: =(B30-$F30)/$F30 -> -0.020275444 | R30: Do not analyze this account
A31: Deferred Revenue (Unearned revenue) | I31: =(B31-D31)/D31 -> #DIV/0! | J31: =(D31-F31)/F31 -> #DIV/0! | L31: =B31/$B$20 -> 0 | M31: =D31/$D$20 -> 0 | N31: =F31/$F$20 -> 0 | P31: =(B31-$F31)/$F31 -> #DIV/0!
A32: Other Liabilities | B32: 6894 | D32: 6091 | F32: 6925 | I32: =(B32-D32)/D32 -> 0.13183385 | J32: =(D32-F32)/F32 -> -0.12043321 | L32: =B32/$B$20 -> 0.0048210026 | M32: =D32/$D$20 -> 0.0042871029 | N32: =F32/$F$20 -> 0.0049935679 | P32: =(B32-$F32)/$F32 -> -0.0044765343
A33: Long term debt (Interest bearing debt)+Leases | B33: 36161 | D33: 45274 | F33: 53849 | I33: =(B33-D33)/D33 -> -0.20128551 | J33: =(D33-F33)/F33 -> -0.15924158 | L33: =B33/$B$20 -> 0.025287536 | M33: =D33/$D$20 -> 0.031865752 | N33: =F33/$F$20 -> 0.038830128 | P33: =(B33-$F33)/$F33 -> -0.32847407
A34: Total Liabilities | B34: =SUM(B29:B33) -> 352064 | D34: =SUM(D29:D33) -> 352224 | F34: =SUM(F29:F33) -> 403375 | I34: =(B34-D34)/D34 -> -0.00045425638 | J34: =(D34-F34)/F34 -> -0.12680756 | L34: =B34/$B$20 -> 0.24619981 | M34: =D34/$D$20 -> 0.24791012 | N34: =F34/$F$20 -> 0.29087082 | P34: =(B34-$F34)/$F34 -> -0.12720421
A35: Other Equity:
A36: Non Controlling Interest (most companies do not have) | I36: =IFERROR((B36-D36)/D36,0) -> 0 | J36: =IFERROR((D36-F36)/F36,0) -> 0 | L36: =B36/$B$20 -> 0 | M36: =D36/$D$20 -> 0 | N36: =F36/$F$20 -> 0 | P36: =(B36-$F36)/$F36 -> #DIV/0!
A37: Preferred Stock (most companies do not have) | I37: =IFERROR((B37-D37)/D37,0) -> 0 | J37: =IFERROR((D37-F37)/F37,0) -> 0 | L37: =B37/$B$20 -> 0 | M37: =D37/$D$20 -> 0 | N37: =F37/$F$20 -> 0 | P37: =(B37-$F37)/$F37 -> #DIV/0!
A38: Common Equity:
A39: Common Stock, Class A and Class B | B39: =100+21 -> 121 | D39: =102+21 -> 123 | F39: =102+21 -> 123 | I39: =(B39-D39)/D39 -> -0.016260163 | J39: =(D39-F39)/F39 -> 0 | L39: =B39/$B$20 -> 8.4615799e-05 | M39: =D39/$D$20 -> 8.6572591e-05 | N39: =F39/$F$20 -> 8.8694418e-05 | P39: =(B39-$F39)/$F39 -> -0.016260163
A40: Additional Paid in Capital (APIC) | B40: 656297 | D40: 629515 | F40: 611622 | I40: =(B40-D40)/D40 -> 0.042543863 | J40: =(D40-F40)/F40 -> 0.029254997 | L40: =B40/$B$20 -> 0.4589512 | M40: =D40/$D$20 -> 0.44307923 | N40: =F40/$F$20 -> 0.44103624 | P40: =(B40-$F40)/$F40 -> 0.073043481
A41: Treasury Stock (a negative number) | I41: =(B41-D41)/D41 -> #DIV/0! | J41: =(D41-F41)/F41 -> #DIV/0! | L41: =B41/$B$20 -> 0 | M41: =D41/$D$20 -> 0 | N41: =F41/$F$20 -> 0 | P41: =(B41-$F41)/$F41 -> #DIV/0!
A42: Retained Earnings | B42: 421568 | D42: 439121 | F42: 371858 | I42: =(B42-D42)/D42 -> -0.039973037 | J42: =(D42-F42)/F42 -> 0.18088356 | L42: =B42/$B$20 -> 0.29480424 | M42: =D42/$D$20 -> 0.30907189 | N42: =F42/$F$20 -> 0.26814414 | P42: =(B42-$F42)/$F42 -> 0.13368006
A43: Other Comprehensive Income (Loss): OCI | B43: -57 | D43: -210 | F43: -194 | I43: =(B43-D43)/D43 -> -0.72857143 | J43: =(D43-F43)/F43 -> 0.082474227 | L43: =B43/$B$20 -> -3.9860335e-05 | M43: =D43/$D$20 -> -0.00014780686 | N43: =F43/$F$20 -> -0.00013989201 | P43: =(B43-$F43)/$F43 -> -0.70618557 | R43: Do not analyze this account
A44: SubTotal Common Equity | B44: =SUM(B39:B43) -> 1077929 | D44: =SUM(D39:D43) -> 1068549 | F44: =SUM(F39:F43) -> 983409 | I44: =(B44-D44)/D44 -> 0.0087782591 | J44: =(D44-F44)/F44 -> 0.086576389 | L44: =B44/$B$20 -> 0.75380019 | M44: =D44/$D$20 -> 0.75208988 | N44: =F44/$F$20 -> 0.70912918 | P44: =(B44-$F44)/$F44 -> 0.096114638
A45: Total Equity | B45: =B44+B37+B36 -> 1077929 | D45: =D44+D37+D36 -> 1068549 | F45: =F44+F36+F37 -> 983409 | I45: =(B45-D45)/D45 -> 0.0087782591 | J45: =(D45-F45)/F45 -> 0.086576389 | L45: =B45/B20 -> 0.75380019 | M45: =D45/$D$20 -> 0.75208988 | N45: =F45/$F$20 -> 0.70912918 | P45: =(B45-$F45)/$F45 -> 0.096114638
A46: TOTAL LIABILITIES AND EQUITY | B46: =B45+B34 -> 1429993 | D46: =D45+D34 -> 1420773 | F46: =F45+F34 -> 1386784 | I46: =(B46-D46)/D46 -> 0.0064894251 | J46: =(D46-F46)/F46 -> 0.024509224 | L46: =L45+L34 -> 1 | M46: =M45+M34 -> 1 | N46: =N45+N34 -> 1 | P46: =(B46-$F46)/$F46 -> 0.0311577
A47: NOTE: Make sure Balance Sheet Balances! Total Assets = Total Liabilities + Total Equity (This line should = 0: TA = TL+OE | B47: =B20-B46 -> 0 | D47: =D20-D46 -> 0 | F47: =F20-F46 -> 0 | I47: Comparative Balance Sheet Analysis: Cash and cash equivalents saw a significant increase over both years, rising 572% in 2022 and continuing to grow by 65% in 2023. While the growth rate slowed in 2023, the continued increase is a favorable trend for liquidity. There was a concerning swing in marketable securities and investments which took a sharp -100% decline in 2022, followed by no reinvestment (0%) in 2023, this follows an unfavorable trend because it means the company was not investing for future growth. Accounts receivable saw a substantial increase, rising from 3% in 2021 to 18% in 2023, despite a decline in sales during the same period. This raises concerns about Boston Beer Company’s ability to efficiently convert sales into cash, as a growing accounts receivable balance alongside declining revenue could indicate that customers are taking longer to pay, making it an unfavorable trend. If this trend continues, it may lead to potential cash flow challenges, making it more difficult for the company to cover its expenses or reinvest in operations. Another concerning shift in current assets was in inventories, which remained unchanged in 2021 (0%) but then declined by 22% in 2023. When paired with decreases in COGS and gross profit over the same period, this indicates an unfavorable trend. If this trend of declining inventory continues, alongside falling gross profit, it raises concerns about the company’s ability to generate revenue and maintain operational stability. In non-current assets, net property, plant, and equipment (PP&E) declined by 4% in 2023, suggesting a slowdown in capital investment—an unfavorable trend that if it continues may impact future operational capacity. Operating right-of-use assets continued to decline, from -17% in 2022 to -19% in 2023, alongside further reductions in other tangible assets and third-party production payments. These unfavorable trends indicate decreased investment in key operational resources, which could hinder future growth and limit efficiency improvements. Conversely, other long-term assets saw substantial growth, increasing by 84% in 2022 and an additional 20% in 2023, signaling a favorable trend. Total assets also grew, at a slower pace, rising 2% in 2022 and 1% in 2023. While asset growth has decelerated, the continued expansion remains a positive indicator, suggesting that Boston Beer Company is still increasing its asset base. Accounts payable, increased by 4% in 2023, reversing the -2% decrease in 2022. This suggests that the company may be taking longer to pay its suppliers. If this trend continues, it could strain supplier relationships, making it an unfavorable trend. Accrued liabilities experienced a significant shift, moving from a -31% decrease in 2022 to a 14% increase in 2023 and is concerning because this increase reflects a rise in outstanding obligations. If this trend continues, along with decreased sales, it could heighten cash flow risks and lead to financial instability, indicating an unfavorable trend. Total current liabilities increased by 9% in 2023, reversing the -20% decrease in 2022, indicating a rise in short-term financial obligations. This unfavorable trend suggests that Boston Beer Company may be relying more on short-term financing, which, if sustained, could lead to liquidity concerns and financial strain. A favorable shift in long-term liabilities was the 11% decrease in deferred income taxes in 2023, following a 10% increase in 2022. This suggests that Boston Beer Company reduced its deferred tax obligations, which may improve its future tax position. However, a key concern is the sharp increase in other liabilities, which shifted from a 12% decrease in 2022 to a 13% increase in 2023. This is an unfavorable trend, as the company is taking on additional long-term obligations while facing declining sales and rising short-term liabilities. If this trend continues, it could place further financial strain on the company and impact its long-term stability. Long-term debt and leases continued to decline, decreasing by 4% from 2022 to 2023, a favorable trend, as it indicates that Boston Beer Company is reducing its long-term financial burdens. Total liabilities decreased by 13% in 2022, indicating that Boston Beer Company made significant progress in reducing its financial obligations. However, in 2023, total liabilities remained unchanged at 0%, suggesting that the company halted further debt reduction. While the prior decrease was positive, if this trend continues, the lack of continued liability reduction could be a concern, especially given rising short-term obligations and declining sales, which makes it an unfavorable trend. A concerning shift in the equity section is the sharp drop in retained earnings, which fell from an 18% increase in 2022 to -4% in 2023. This suggests that Boston Beer Company either experienced net losses or distributed large dividends to shareholders, potentially weakening its financial stability. This follows an unfavorable trend because a decline in retained earnings reduces the company's ability to reinvest in operations or help with any future financial challenges. Other comprehensive income (OCI) saw a sharp decline, shifting from an 8% increase to a 73% decrease in 2023, indicating a significant rise in unrealized losses. This is an unfavorable trend because it paints a picture of increased financial pressure in these areas and if it continues it could further weaken the company’s overall financial position and reduce shareholder equity. The 9% increase in 2022 followed by a slower 1% increase in 2023 for total equity suggests that while equity is still growing, the pace of growth has significantly slowed. While still a favorable trend, the slowdown in equity growth may signal financial headwinds that could limit the company’s ability to fund future expansion. | L47: Common Size Balance Sheet: Current assets as a percentage of total assets increased by 5% each year from 2021 to 2023, which is a favorable trend as it indicates that a larger portion of Boston Beer Company's assets are more liquid. Specifically, cash and cash equivalents rose from 2% in 2021 to 21% in 2023, further strengthening the company’s liquidity position. However, marketable securities and investments grew by 3% in 2021 but remained unchanged at 0% in both 2022 and 2023. This is an unfavorable trend, suggesting that Boston Beer Company has not been allocating resources toward investments to generate future returns, potentially limiting future growth. Inventory as a percentage of total assets continuously declined from 2021 to 2023, with a 2% drop from 2022 to 2023. This is an unfavorable trend, as sales also decreased during the same period, indicating that inventory reduction is not a result of strong business operations but rather lower demand. For long-term assets, net property, plant, and equipment (PP&E) remains the largest component, though it declined from 2021 to 2023, with the most significant drop occurring from 47% in 2022 to 45% in 2023. This is an unfavorable trend, as it suggests a reduction in asset expansion. Operating right-of-use assets as a percentage of total assets have seen a steady decline, with a 1% decrease each year from 2021 to 2023. This is an unfavorable trend, as it may indicate reduced investment in leased assets, potentially impacting the company’s operational flexibility and long-term growth potential. Other intangibles have also declined steadily each year from 2021 to 2023, with the largest percentage drop occurring from 7% in 2021 to 5% in 2022. Additionally, third-party production prepayments decreased by 2% each year over the same period. These represent unfavorable trends, indicating that Boston Beer Company's non-current assets are in decline, which could impact the company's long-term growth and strategic flexibility. Conversely, other long-term assets increased from 1% in 2021 to 3% in 2022 and remained steady at 3% in 2023, representing a favorable trend as it suggests stability or growth in certain non-current asset categories. Total current liabilities, as a percentage of total assets, decreased from 18% in 2021 to 14% in 2022 but then increased to 16% in 2023. This fluctuation could indicate inconsistent short-term financial management. While the decline in current liabilities from 2021-2022 is favorable as it suggests lower short-term obligations, the subsequent increase in 2023 is unfavorable and raises concerns about rising short-term debt or operational costs. Accrued liabilities experienced the most significant fluctuations, dropping from 12% in 2021 to 8% in 2022 before rising again to 9% in 2023. This trend suggests variability in the company's short-term obligations and is an unfavorable trend. Total liabilities as a percentage of total assets declined from 29% in 2021 to 25% in 2022, where it remained in 2023. This is a favorable trend, as it indicates a reduction in financial leverage and suggests that Boston Beer Company has improved its ability to manage long-term obligations relative to its assets. In the equity section, total equity increased from 71% in 2021 to 75% in 2022 and remained at 75% in 2023. This is a favorable trend, indicating that Boston Beer Company has strengthened its financial position by relying more on equity rather than liabilities, which reduces financial risk. Additional paid-in capital saw an increase from 44% in 2022 to 46% in 2023, which indicates a favorable trend, as it suggests the company raised additional capital. Retained earnings saw a significant increase from 27% in 2021 to 31% in 2022, but then experienced a sharp decline to 29% in 2023. This up-and-down shifting is a mixed trend, the initial increase suggests profitability and reinvestment into the business which is favorable, but the subsequent decline is unfavorable. The decline indicates higher dividend payouts, increased expenses, reduced net income, or a mixture of all three and if this trend continues would raise concerns about sustainability. | P47: Trend Analysis: Boston Beer Company's financial trends reflect a mixed financial picture, balancing strengthened liquidity with reductions in key assets and liabilities in response to declining sales. While some trends indicate improved financial stability, others raise concerns about future growth and strategic investments. One of the most favorable trends is the 1,012% increase in cash and cash equivalents, which suggests that the company has prioritized liquidity—possibly as a safeguard against lower revenue. Additionally, retained earnings grew by 13%, indicating that the company remained profitable despite declining sales, likely through cost-cutting or operational efficiencies. The 7% increase in additional paid-in capital reflects continued investor confidence, suggesting that external funding sources remain available. Other long-term assets surged by 120%, which could indicate strategic investments. However, it remains uncertain whether these assets will generate sufficient returns amid lower sales. The 71% reduction in comprehensive income loss is another positive trend, as it suggests that fewer losses are impacting equity, strengthening the company’s overall financial position. Since the company’s cash reserves have surged while sales have declined, the 100% reduction in marketable securities suggests a shift toward cash conservation. If this was a proactive strategy to enhance liquidity, it can be seen as a favorable trend. Several trends raise concerns about future growth and operational sustainability. The 22% decline in inventories suggests weaker demand or an effort to clear excess stock. Additionally, net property, plant, and equipment (PP&E) declined by 3%, signaling reduced capital expenditures, which could slow long-term expansion. The 33% drop in operating right-of-use assets and the 42% decline in other intangibles may reflect asset impairments or divestments, possibly as a way to adjust to the lower sales environment. Furthermore, the 62% reduction in third-party production prepayments signals a significant pullback on future production commitments, aligning with sales declines and suggesting a more cautious approach to resource allocation. On the liabilities side, long-term debt and leases declined by 33%, which could be viewed positively as it reduces financial obligations. However, it may also indicate that the company is avoiding new investments or expansion, potentially limiting future growth. Similarly, accrued liabilities fell by 21%, likely due to reduced operating expenses, but this could also suggest aggressive cost-cutting that might impact business operations.
A49: Insert Company Name
A50: Statement of Owner's Equity
A51: Year Ending ? (insert Month & day)
A52: (in thousands or millions?) 7 pts EXTRA CREDIT | B52: =B4 -> 2023 | D52: =D4 -> 2022 | F52: =F4 -> 2021
A53: Beginning Balance | B53: =D62 -> 81816 | D53: =F62 -> 14553 | F53: Input this number
A54: Add: Net Income (This must = Income Stmt) | B54: =B85 -> 76250 | D54: =D85 -> 67263 | F54: =F85 -> 14553
A55: Other Comprehensive Income (Loss): OCI
A56: Sales of Stock
A57: Stock based compensation
A58: Less: Dividends Declared (show as “-“ amounts)
A59: Stock repurchases (Treasury Stock)
A61: Adjustments for foreign currency & other
A62: Ending Balance Capital (Note: Should = “SubTotal Common Equity" on Balance Sheet) | B62: =SUM(B53:B61) -> 158066 | D62: =SUM(D53:D61) -> 81816 | F62: =SUM(F53:F61) -> 14553
A64: Boston Beer Company Inc Income Statement December 30- December 31 | I64: Boston Beer Company Inc Comparative Income Statement December 2023 | L64: Boston Beer Company Inc Common Sized Income Statement December 30 - December 31 | P64: Boston Beer Compnay Inc Trend Analysis Income Statement December 30 - December 31
A67: (in thousands or millions?) | B67: =B4 -> 2023 | D67: =D4 -> 2022 | F67: =F4 -> 2021 | I67: =B67 -> 2023 | J67: =D67 -> 2022 | L67: =B67 -> 2023 | M67: =D67 -> 2022 | N67: =F67 -> 2021 | P67: =B4 -> 2023
A68: Sales | B68: 2008625 | D68: 2090334 | F68: 2057622 | I68: =(B68-D68)/D68 -> -0.039088969 | J68: =(D68-F68)/F68 -> 0.015897964 | L68: =B68/$B$68 -> 1 | M68: =D68/$D$68 -> 1 | N68: =F68/$F$68 -> 1 | P68: =(B68-$F68)/$F68 -> -0.02381244
A69: Cost of Goods Sold | B69: 1156256 | D69: 1228348 | F69: 1259830 | I69: =(B69-D69)/D69 -> -0.058690208 | J69: =(D69-F69)/F69 -> -0.024989086 | L69: =B69/$B$68 -> 0.57564553 | M69: =D69/$D$68 -> 0.58763241 | N69: =F69/$F$68 -> 0.61227475 | P69: =(B69-$F69)/$F69 -> -0.082212679
A70: Gross Profit | B70: =B68-B69 -> 852369 | D70: =D68-D69 -> 861986 | F70: =F68-F69 -> 797792 | I70: =(B70-D70)/D70 -> -0.011156794 | J70: =(D70-F70)/F70 -> 0.080464582 | L70: =B70/$B$68 -> 0.42435447 | M70: =D70/$D$68 -> 0.41236759 | N70: =F70/$F$68 -> 0.38772525 | P70: =(B70-$F70)/$F70 -> 0.068410062
A71: Selling / Marketing Expenses | B71: 555998 | D71: 578400 | F71: 606994 | I71: =(B71-D71)/D71 -> -0.038730982 | J71: =(D71-F71)/F71 -> -0.04710755 | L71: =B71/$B$68 -> 0.27680528 | M71: =D71/$D$68 -> 0.27670219 | N71: =F71/$F$68 -> 0.29499782 | P71: =(B71-$F71)/$F71 -> -0.08401401
A72: impairment of brewery assets | B72: 5396 | D72: 2782 | F72: 18499 | I72: =(B72-D72)/D72 -> 0.93961179 | J72: =(D72-F72)/F72 -> -0.84961349 | L72: =B72/$B$68 -> 0.0026864148 | M72: =D72/$D$68 -> 0.0013308878 | N72: =F72/$F$68 -> 0.0089904754 | P72: =(B72-$F72)/$F72 -> -0.70830856
A73: impairment of intangible assets | B73: 16426 | D73: 27100 | F73: 0 | I73: =IFERROR((B73-D73)/F73,0) -> 0 | J73: =IFERROR((D73-F73)/F73,0) -> 0 | L73: =B73/B68 -> 0.0081777335 | M73: =D73/D68 -> 0.012964435 | N73: =F73/F68 -> 0 | P73: =IFERROR((B73-F73)/F73,0) -> 0
A74: contract termination costs and other | D74: 5379 | F74: 30678 | I74: =(B74-D74)/F74 -> -0.17533738 | J74: =(D74-F74)/F74 -> -0.82466262 | L74: =B74/B68 -> 0 | M74: =D74/D68 -> 0.002573273 | N74: =F74/F68 -> 0.014909444 | P74: =(B74-F74)/F74 -> -1
A75: General & Admin Expenses | B75: 174548 | D75: 157534 | F75: 133624 | I75: =(B75-D75)/D75 -> 0.10800208 | J75: =(D75-F75)/F75 -> 0.17893492 | L75: =B75/$B$68 -> 0.086899247 | M75: =D75/$D$68 -> 0.075363076 | N75: =F75/$F$68 -> 0.064940985 | P75: =(B75-$F75)/$F75 -> 0.30626235
A76: Total Operating Expenses | B76: =SUM(B71:B75) -> 752368 | D76: =SUM(D71:D75) -> 771195 | F76: =SUM(F71:F75) -> 789795 | I76: =(B76-D76)/D76 -> -0.024412762 | J76: =(D76-F76)/F76 -> -0.023550415 | L76: =B76/$B$68 -> 0.37456867 | M76: =D76/$D$68 -> 0.36893386 | N76: =F76/$F$68 -> 0.38383872 | P76: =(B76-$F76)/$F76 -> -0.047388246
A77: Operating Profit (EBIT: Earnings before Interest & Taxes) | B77: =B70-B76 -> 100001 | D77: =D70-D76 -> 90791 | F77: =F70-F76 -> 7997 | I77: =(B77-D77)/D77 -> 0.10144177 | J77: =(D77-F77)/F77 -> 10.353132 | L77: =B77/$B$68 -> 0.049785799 | M77: =D77/$D$68 -> 0.043433729 | N77: =F77/$F$68 -> 0.0038865253 | P77: =(B77-$F77)/$F77 -> 11.504814
A78: Non-Operating Income/Gain (Expense/Loss):
A79: Add: Other Income (eg, Investment /Interest Income, Gains) | B79: 10995 | D79: 2561 | F79: -110 | I79: =(B79-D79)/D79 -> 3.2932448 | J79: =(D79-F79)/F79 -> -24.281818 | L79: =B79/$B$68 -> 0.0054738938 | M79: =D79/$D$68 -> 0.0012251631 | N79: =F79/$F$68 -> -5.3459771e-05 | P79: =(B79-$F79)/$F79 -> -100.95455
A80: Subtract: (Interest Expense) (show as a -#) | B80: -1408 | D80: -1916 | F80: -978 | I80: =(B80-D80)/D80 -> -0.2651357 | J80: =(D80-F80)/F80 -> 0.9591002 | L80: =B80/$B$68 -> -0.00070097704 | M80: =D80/$D$68 -> -0.00091659993 | N80: =F80/$F$68 -> -0.00047530596 | P80: =(B80-$F80)/$F80 -> 0.4396728
A81: (Other Losses) (show as a -#) | I81: =IFERROR((B81-D81)/D81,0) -> 0 | J81: =IFERROR((D81-F81)/F81,0) -> 0 | L81: =B81/$B$68 -> 0 | M81: =D81/$D$68 -> 0 | N81: =F81/$F$68 -> 0 | P81: =IFERROR((B81-$F81)/$F81,0) -> 0
A82: Net Non-Operating Income (Expense) | B82: =SUM(B79:B81) -> 9587 | D82: =SUM(D79:D81) -> 645 | F82: =SUM(F79:F81) -> -1088 | I82: =(B82-D82)/D82 -> 13.863566 | J82: =(D82-F82)/F82 -> -1.5928309 | L82: =B82/$B$68 -> 0.0047729168 | M82: =D82/$D$68 -> 0.00030856313 | N82: =F82/$F$68 -> -0.00052876573 | P82: =(B82-$F82)/$F82 -> -9.8115809
A83: Earnings Before Taxes (EBT) | B83: =B77+B82 -> 109588 | D83: =D77+D82 -> 91436 | F83: =F77+F82 -> 6909 | I83: =(B83-D83)/D83 -> 0.19852137 | J83: =(D83-F83)/F83 -> 12.234332 | L83: =B83/$B$68 -> 0.054558716 | M83: =D83/$D$68 -> 0.043742292 | N83: =F83/$F$68 -> 0.0033577596 | P83: =(B83-$F83)/$F83 -> 14.86163
A84: Income Tax Expense (aka, provision) | B84: 33338 | D84: 24173 | F84: -7644 | I84: =(B84-D84)/D84 -> 0.37914202 | J84: =(D84-F84)/F84 -> -4.1623496 | L84: =B84/$B$68 -> 0.016597424 | M84: =D84/$D$68 -> 0.011564181 | N84: =F84/$F$68 -> -0.0037149681 | P84: =(B84-$F84)/$F84 -> -5.3613291
A85: Net Income (do not subtract noncontrolling interests) | B85: =B83-B84 -> 76250 | D85: =D83-D84 -> 67263 | F85: =F83-F84 -> 14553 | I85: =(B85-D85)/D85 -> 0.13360986 | J85: =(D85-F85)/F85 -> 3.6219336 | L85: =B85/$B$68 -> 0.037961292 | M85: =D85/$D$68 -> 0.032178111 | N85: =F85/$F$68 -> 0.0070727276 | P85: =(B85-$F85)/$F85 -> 4.2394695
A86: NOTE: MAKE SURE THE NET INCOME ABOVE = THE NET INCOME IN THE STATEMENT OF OWNER’S EQUITY AND IN THE STATEMENT OF CASH FLOWS. | L86: Common size income statement analysis: Boston Beer Company’s financial performance has shown increasing net income as a percentage of sales over the past three years, but some concerning trends suggest potential sustainability issues. Net income increased from 1% in 2021 to 3% in 2022 and 4% in 2023, reflecting improved profitability. Income tax expense also rose from 1% in 2022 to 2% in 2023, aligning with higher earnings. Overall, net income represents a favorable trend as profitability has improved. Earnings before interest and taxes (EBIT) also increased from 0% in 2021 to 4% in 2022 and 5% in 2023, which would typically be viewed as a positive shift. However, this increase appears to be driven by reduced inventory levels and the sale of investments rather than organic business growth, making it an unsustainable trend if sales continue to decline. Cost of goods sold (COGS) declined from 61% in 2021 to 58% in 2023, which would generally indicate improved cost efficiency. However, with sales declining during this same period, the lower COGS is likely due to reduced production and demand rather than genuine efficiency improvements, making it an unfavorable trend. Gross profit increased from 39% in 2021 to 42% in 2023, which under normal circumstances would be favorable. However, since this rise is not the result of increased sales or operational efficiencies, it raises concerns about the company’s ability to sustain profitability in the long run, making this an unfavorable trend as well. Operating expenses also reflect some challenges, particularly with general and administrative (G&A) expenses, which increased from 6% in 2021 to 9% in 2023. This is an unfavorable trend, as rising administrative costs put pressure on profitability, especially when sales are declining. To maintain long-term financial stability, Boston Beer Company must shift its focus toward generating sustainable revenue growth rather than relying on cost-cutting measures and asset sales. | P86: Trend Analysis: Boston Beer Company’s income statement trend analysis reveals significant shifts in financial performance over the period. Sales declined by 2%, indicating a slight drop in revenue which is an unfavorable trend. Cost of goods sold (COGS) decreased by 8%, which outpaced the decline in sales. While a lower COGS typically improves margins, in this case, it is an unfavorable tend due to reduced production and demand, not true cost efficiencies. As a result, gross profit increased by 7%, reflecting a stronger profit margin despite declining sales, indicating a favorable trend but raises concerns about Boston Beer Company’s future profitability. In operating expenses, marketing expenses decreased by 8%, which indicates cost-cutting efforts and a reduction in promotional activities that might impact future sales growth indicating an unfavorable trend. General and administrative (G&A) expenses, on the other hand, increased by 31%, which is a concerning trend as higher administrative costs put additional pressure on profitability, making it an unfavorable trend. Overall, total operating expenses declined by 5%, driven by reductions in marketing and contract termination costs, with the latter experiencing a 100% decrease. Additionally, impairment of brewery assets declined by 71%, indicating fewer write-downs on asset values. Which makes total operating expenses a favorable trend. Earnings before interest and taxes (EBIT) saw an extraordinary 1,150% increase, reflecting significantly improved profitability. However, this sharp rise is likely due to non-recurring factors such as cost reductions and asset sales rather than sustainable revenue growth, making it a favorable trend but it raises serious concerns over sustainability due to Boston Beer Company's decreased sales. Similarly, earnings before taxes (EBT) surged by 1,486%, and net income increased by 424%, demonstrating a substantial boost in bottom-line profitability, both following favorable trends. However, the extreme volatility in net non-operating income (a decline of 981% and unfavorable trend) suggests that non-operating items had a major impact on overall financial results, potentially distorting the true profitability of the company’s core operations.
I87: Comparative income statement: Sales showed a troubling outlook, as revenue declined by 4% in 2023 after a 2% increase in 2022, indicating an unfavorable trend. The cost of goods sold (COGS) fell by 6%, a more substantial decline than the 2% drop in 2022. While a reduction in COGS is typically a positive indicator of cost efficiency, in this case, when combined with the sharp drop in inventory from the balance sheet and declining sales, it suggests lower production volumes rather than improved efficiency, making it an unfavorable trend. Gross profit declined by 1% in 2023, a stark contrast to the 8% increase seen in 2022. This indicates that despite lower COGS, the declining sales offset any potential profitability gains, signaling a weakening performance at the core business level, which is an unfavorable trend. Operating expenses were managed effectively, with selling and marketing expenses decreasing by 4%, slightly improving upon the 5% reduction in 2022. Due to selling and marketing expenses only having a moderate drop and not aligning with the drastic drop in sales, this would reflect good financial management on Boston Beer Company's part and would be a favorable trend. General administrative expenses continued to rise, increasing by 11%, though at a slower pace compared to the 18% increase in 2022. When combined with the decrease in sales, this indicates an unfavorable trend, as expenses are still increasing while revenue declines. Overall, total operating expenses remained stable at a -2% change. This shows that despite the fluctuations in many individual expense categories, Boston Beer Company has been able to demonstrate effective cost-control measures, making this a favorable trend. Operating profit (EBIT) surged by 1035% in 2022, followed by a more modest 10% growth in 2023. While the continued rise in operating profit is positive, it falls significantly short of the extraordinary increase seen in the prior year. This suggests that the previous surge was likely driven by one-time cost reductions rather than sustainable profit growth, indicating an unfavorable trend. Asset impairments presented a significant concern, with the impairment of brewery assets skyrocketing by 94% in 2023, reversing the 85% reduction in 2022. This major write-down negatively impacts profitability, making it an unfavorable trend. Contract termination costs continued to decline, dropping by 18% after an 82% reduction in 2022. This highlights a decreasing reliance on costly contract adjustments on Boston Beer Company's part, making it a favorable trend. Non-operating income showed a substantial recovery, with other income and investment gains rebounding by 329%, compared to a severe -2428% decline in 2022. This suggests a strong recovery in investment-related earnings, marking it as a favorable trend. However, earnings before taxes growth slowed significantly, rising by only 20% in 2023, far below the 1223% increase in 2022. This indicates, once again, that non-core revenue sources are stabilizing rather than driving major profitability gains. If this trend continues, Boston Beer Company could face financial difficulties, making this an unfavorable trend. Tax expenses further highlight the company's changing financial position. In 2023, income tax expense increased by 38%, contrasting sharply with the tax benefit of -416% in 2022. Given that much of the company's profitability appears to have come from investment-related gains rather than strong operational performance, this increase in tax expense is likely due to taxable gains from non-operating income rather than sustainable business growth. This is an unfavorable trend, as it reflects a reliance on temporary financial gains rather than core business profitability. Despite these financial shifts, net income grew by 13% in 2023, though this represents a considerable slowdown compared to the 362% increase in 2022. While profitability continues to improve, the reduced growth rate suggests that the extraordinary gains from internal sources from previous years are no longer fueling the bottom line at the same pace. If this trend continues, the company will exhaust their internal factors putting future profitability at risk, making this an unfavorable trend.
A88: Boston Beer Company Inc Statement of Cash Flows Year Ending December 30
A91: (in thousands or millions?) | B91: =B67 -> 2023 | D91: =D67 -> 2022 | F91: =F67 -> 2021 | I91: Answers to Question I
A92: Cash flow from Operating activities: | I92: I1) OPERATING ACTIVITIES:
A93: Net Income (This must = Income Stmt) | B93: =B85 -> 76250 | D93: =D85 -> 67263 | F93: =F85 -> 14553 | I93: Boston Beer Company’s operations have significantly improved over the past three years. The company has generated positive cash flows from operations in all three years with 56.3 million in 2021, 199.9 million in 2022 and 265.2 million in 2023. While 2021's cash flow was relatively weak and caused a funding gap of 90.3 million dollars, the company significantly improved its operating cash flow in 2022 and 2023, leaving them with a surplus of 111.4 million in 2023 and 202.8 million in 2022. However, much of this improvement was due to cost-cutting, inventory reductions, and the elimination of investments, rather than strong sales growth. So while cash flow from operations was positive each year, the long-term sustainability of these improvements depends on whether the company can stabilize or grow its sales rather than relying on one-time cost reductions.
A94: Discontinued Operations/Extraordinary Items onbottom of Inc. Stmt
A95: Depreciation and amortization | B95: 88141 | D95: 81356 | F95: 72096
A96: impairment of intangible asset | B96: =16426 -> 16426 | D96: 27100 | F96: 0
A97: Impairment of brewery asset | B97: =5396 -> 5396 | D97: 2782 | F97: 18499
A98: Change in right of use assets | B98: =7678 -> 7678 | D98: 7972 | F98: 8018
A99: stock-based compensation expense | B99: =16971 -> 16971 | D99: 13988 | F99: 18615
A100: deferred income taxes | B100: -10871 | D100: 9097 | F100: -5225
A101: Share Based Compensation
A102: Other non-cash expense (income) | B102: 224 | D102: 89 | F102: -399
A103: (Gains)/Losses
A104: Change in Current Operating Assets & Liabilities:
A105: Change in A/R | B105: -10340 | D105: -2042 | F105: 23071
A106: Change in Inventories | B106: 31500 | D106: 131 | F106: -21224
A107: Change in prepaids | B107: 13979 | D107: 38652 | F107: -49073
A108: third-party production payments | B108: 27758 | D108: 26955 | F108: -16635
A109: other assets | B109: -5849 | D109: -14031 | F109: -5699
...

Sheet Ratios
A1: Company Name | B1: Boston Beer Company Inc | H1: Is the Ratio Trend "Favorable","Unfavorable" or "Stable"? | I1: Is the ratio itself "Favorable" or "Unfavorable"? | J1: Interpretation/Implications of each ratio
A2: Student Name | B2: Laura Dampman
A3: Ratio Analysis | B3: ='Finl Stmts'!B4 -> 2023 | D3: ='Finl Stmts'!D4 -> 2022 | F3: ='Finl Stmts'!F4 -> 2021
A4: Liquidity Ratios: any Going Concern issues? Can the firm stay in business in the short term? Should lenders extend credit to this firm?
A5: Current Ratio: measures ability to pay short term debt, but has problem with inventory value and quality of A/R | H5: Trend favorable | I5: In 2021 unfavorable and for 2022 to 2023 favorable | J5: Boston Beer Company's quick ratio showed a favorable trend overall, with the ratio improving each year reflecting improved liquidity. However, in 2021, the ratio itself was unfavorable, indicating liquidity challenges. With total current assets of $345,341 and total current liabilities of $255,106, the company may have struggled to meet short-term obligations. Which is reflected in the funding gap and low operating cash flows for 2021. The company's ratio saw significant improvement in 2022, reflecting better short term financial stability and is reflected in the large increase in cash and cash equivalents in 2022 on the balance sheet. In 2023, the ratio improved but at a much slower pace compared to 2022. This is concerning because while the company is improving their liquidity, the concern is that excess liquidity is not being invested for future growth which is supported by the company's negative investing cash flows from both 2022 and 2023.
A6: Current assets | B6: ='Finl Stmts'!B11 -> 503510 | C6: =B6/B7 -> 2.2549801 | D6: ='Finl Stmts'!D11 -> 423269 | E6: =D6/D7 -> 2.072136 | F6: ='Finl Stmts'!F11 -> 345341 | G6: =F6/F7 -> 1.3537157
A7: Current liabilities | B7: ='Finl Stmts'!B29 -> 223288 | D7: ='Finl Stmts'!D29 -> 204267 | F7: ='Finl Stmts'!F29 -> 255106
A9: Quick Ratio: measures ability to easily pay short term debt & avoids problem of inventory value, but still has A/R quality issue | H9: Trend favorable | I9: In 2021 unfavorable and for 2022 to 2023 favorable | J9: Boston Beer Company’s quick ratio showed a favorable trend overall, improving from 0.5 in 2021 to 1.2 in 2022 and 1.6 in 2023, indicating a stronger liquidity position each year. In 2021, the company faced liquidity struggles, with low cash and receivables relative to its liabilities and no reliance on external financing. By 2022, liquidity improved as operating cash flows strengthened, providing better short-term financial stability. In 2023, the quick ratio increased further, suggesting strong financial health, though excess liquidity raises concerns about inefficient reinvestment. Despite improving liquidity, declining sales across all three years indicate that these improvements were driven more by asset management and cost control rather than revenue growth.
A10: Cash + marketable securities + Net A/R | B10: ='Finl Stmts'!B6+'Finl Stmts'!B7+'Finl Stmts'!B8 -> 365488 | C10: =B10/B11 -> 1.6368457 | D10: ='Finl Stmts'!D6+'Finl Stmts'!D7+'Finl Stmts'!D8 -> 237232 | E10: =D10/D11 -> 1.1613819 | F10: ='Finl Stmts'!F6+'Finl Stmts'!F7+'Finl Stmts'!F8 -> 121343 | G10: =F10/F11 -> 0.47565718
A11: Current liabilities | B11: ='Finl Stmts'!B29 -> 223288 | D11: ='Finl Stmts'!D29 -> 204267 | F11: ='Finl Stmts'!F29 -> 255106
A13: Cash Ratio: conservative variation of Quick Ratio: no A/R quality issue & no inventory valuation issue | H13: Favorable trend | I13: In 2021 unfavorable, for 2022 moderate to stable and in 2023 favorable | J13: Boston Beer Company's cash ratio has shown an overall favorable trend, indicating improved liquidity and a reduced risk of short-term financial distress. In 2021, the company’s cash ratio was unfavorable, signaling that it did not have enough cash to fully cover its current liabilities. By 2022, liquidity had improved, though the ratio remained below the favorable threshold at 88%. In 2023, the ratio moved into the favorable range, suggesting that the company could comfortably meet its short-term liabilities. However, a cash ratio that is too high may also indicate inefficiency, as excess cash sitting idle is not being reinvested to generate returns or support future growth.
A14: Cash + Marketable Securities | B14: ='Finl Stmts'!B6+'Finl Stmts'!B7 -> 298491 | C14: =B14/B15 -> 1.3367982 | D14: ='Finl Stmts'!D6+'Finl Stmts'!D7 -> 180560 | E14: =D14/D15 -> 0.88394112 | F14: ='Finl Stmts'!F6+'Finl Stmts'!F7 -> 66321 | G14: =F14/F15 -> 0.25997429
A15: Current liabilities | B15: ='Finl Stmts'!B29 -> 223288 | D15: ='Finl Stmts'!D29 -> 204267 | F15: ='Finl Stmts'!F29 -> 255106
A17: Sustainable cash flow: Cash available to pay investors And invest extra for higher future growth rates in sales | J17: The trend in Boston Beer Company's sustainable cash flow is favorable, as the company has improved its ability to generate cash available for investors and reinvestment over the past three years. Sustainable cash flow increased significantly from a negative value in 2021,an unfavorable position, to a positive value in 2022, then nearly doubled in 2023. However, while the cash flow trend appears positive, it is crucial to recognize that Boston Beer Company's operational cash flow is not driven by strong core business performance, as sales have declined. If core sales continue to fall, this improvement may not be sustainable in the long term. Instead, the company may simply be temporarily covering deeper financial issues, much like placing a bandage over a widening gap.
A18: Cash flow from operations (Stmt of CF) - Capital expenditures (Tangible & Intangible asset purchases) | B18: ='Finl Stmts'!B114+'Finl Stmts'!B118+'Finl Stmts'!B122 -> 201064 | D18: ='Finl Stmts'!D114+'Finl Stmts'!D118+'Finl Stmts'!D122 -> 109363 | F18: ='Finl Stmts'!F114+'Finl Stmts'!F118+'Finl Stmts'!F122 -> -91622 | H18: Trend favorable | I18: In 2021 unfavorable and for 2022 to 2023 favorable
A20: Cash flow ratio: Ability of cash flow from operations to pay obligations as they become due. | H20: Trend favorable | I20: In 2021 unfavorable, in 2022 moderate to stable and in 2023 favorable | J20: Boston Beer Company's cash flow ratio has shown an overall favorable trend, steadily improving over the past three years. In 2021, the ratio, 0, was unfavorable and considered high risk, as the company did not generate enough operational cash flow to cover its short-term liabilities, relying instead on debt sales to meet its obligations. By 2022, the ratio improved to 1, with operational cash flow improving, though it still fell short of fully covering short-term liabilities. In 2023, the company finally had enough cash flow from operations to fully cover their short term debt while still having some excess cash remaining. This progression indicates that Boston Beer Company moved from financial strain to stability and now enjoys strong liquidity, which would typically position a company well for future growth and investment. However, a key concern is that much of the company’s operational cash flow over this period came from the liquidation of inventory and debt sales, rather than increased sales revenue. Since overall sales declined, relying on internal asset sales and debt to generate cash is unsustainable in the long run, as there is only so much a company can liquidate before depleting its resources.
A21: Cash flow from operations (Stmt of CF) | B21: ='Finl Stmts'!B114 -> 265151 | C21: =B21/B22 -> 1.1874843 | D21: ='Finl Stmts'!D114 -> 199945 | E21: =D21/D22 -> 0.97884142 | F21: ='Finl Stmts'!F114 -> 56297 | G21: =F21/F22 -> 0.22068082
A22: Current liabilities | B22: ='Finl Stmts'!B29 -> 223288 | D22: ='Finl Stmts'!D29 -> 204267 | F22: ='Finl Stmts'!F29 -> 255106
A24: Asset Management /Activity Ratios
B25: =B3 -> 2023 | D25: =D3 -> 2022 | F25: =F3 -> 2021
A26: Inventory turnover ratio: # times sell and replace inventory during the year | H26: Trend is stable | I26: In 2021 favorable, in 2022 unfavorable and 2023 favorable agian | J26: Boston Beer Company's inventory turnover ratio is slightly favorable/stable. In 2021, with a ratio of 8.4, it shows that company sold and replaced inventory at a reasonable pace. In 2022 the company's ratio, at 8.4, indicates a slight decrease in turnover suggesting that inventory was moving more slowly. This could have led to potentially higher costs or excess stock, indicating inefficiencies in demand and inability to sell inventory quick enough. Which most certainly put pressure on Boston Beer Company's cash flow. In 2023 the increase in turnover suggest improved inventory efficiency. However with inventory dropping by -22% and sales declining during the same time period, this would indicate that the improvement was not due to higher demand but rather cost cutting measures or liquidation. This poses sustainability risks if demand doesn’t rebound and sales increase.
A27: Cost of Goods Sold | B27: ='Finl Stmts'!B69 -> 1156256 | C27: =B27/B28 -> 8.7521223 | D27: ='Finl Stmts'!D69 -> 1228348 | E27: =D27/D28 -> 8.2559146 | F27: ='Finl Stmts'!F69 -> 1259830 | G27: =F27/F28 -> 8.4485441
A28: Average Inventory | B28: =('Finl Stmts'!B9+'Finl Stmts'!D9)/2 -> 132111.5 | D28: =('Finl Stmts'!D9+'Finl Stmts'!F9)/2 -> 148784 | F28: =('Finl Stmts'!F9) -> 149118
A30: Days in Inventory / Inventory Conversion Period: The average time required to convert raw materials into finished goods (or to purchase products) and then to sell them. | J30: Boston Beer Company's inventory conversion period in 2021 was favorable at 43 days, indicating the company was efficiently managing its inventory with a good balance between supply and demand, reducing the risk of excess stock. In 2022, the ratio showed that inventory turnover remained steady, with a slight increase to 44 days, which is somewhat concerning but still suggests continued efficiency. In 2023, the ratio remained favorable as the days in inventory decreased to 42 days, indicating that products were moving more quickly. While this would typically suggest strong product demand, the company's declining sales in 2023 suggest otherwise. Instead, the decrease in days in inventory likely indicates that Boston Beer Company was liquidating its inventory or offering discounts to clear excess stock.
A31: 365 | B31: =365 -> 365 | C31: =B31/B32 -> 41.704171 | D31: =365 -> 365 | E31: =D31/D32 -> 44.210729 | F31: =365 -> 365 | G31: =F31/F32 -> 43.20271
A32: Inventory Turnover Ratio | B32: =C27 -> 8.7521223 | D32: =E27 -> 8.2559146 | F32: =G27 -> 8.4485441 | H32: Trend is favorable | I32: Favorable in 2021,2022 and 2023
A34: Days Sales Outstanding (DSO) / Receivables Collection Period: The average time to collect cash from credit sales | J34: Boston Beer Company's receivables collection period ratios shows an unfavorable trend with 2021 and 2022's ratio remaining favorable at 10 but then 2023's ratio increasing to 12 which is still efficient but concerning that it is growing. In 2021 and 2022 the company collected payments from customers quickly, well within its 30 day credit policy. In 2023 the ratio slightly grew to 12 but is still far below the company's 30 day credit policy. However the rising trend could indicate slower payments which warrant closer monitoring to prevent future cash flow issues.
A35: Net Receivables | B35: ='Finl Stmts'!B8 -> 66997 | C35: =B35/B36 -> 12.17445 | D35: ='Finl Stmts'!D8 -> 56672 | E35: =D35/D36 -> 9.8956817 | F35: ='Finl Stmts'!F8 -> 55022 | G35: =F35/F36 -> 9.7603107 | H35: Trend is unfavorable | I35: In 2021 favorable, 2022 favorable and 2023 unfavorable
A36: Avg Credit Sales per day (Annual credit sales/365) | B36: ='Finl Stmts'!B68/365 -> 5503.0822 | D36: ='Finl Stmts'!D68/365 -> 5726.9425 | F36: ='Finl Stmts'!F68/365 -> 5637.3205
A37: Note: Assume the company credit policy is 30 days
A39: Payables turnover (in days)/Payables Deferral Period: Average time between the purchase of materials, labor & products & payment of cash for them | J39: Boston Beer Company's payable turnover ratio is overall unfavorable with the days to pay suppliers increasing over time. The ratio for the years 2021 and 2022 were stable, taking the company about 15 days to pay suppliers which is a reasonable time frame. Since 2021 and 2022 ratios are stable, this suggests consistent payment practices for those years. In 2023, there was an increase in the payment period suggesting the company is taking slightly longer to pay its suppliers. This is further confirmed with the company's balance sheet, showing an increase in the accounts payable amount for 2023. Delaying payments to suppliers could be a strategic move on the company's part to conserve cash, however if this trend were to continue it would strain future supplier relationships.
A40: 365 | B40: 365 | C40: =B40/B41 -> 27.067944 | D40: 365 | E40: =D40/D41 -> 25.282461 | F40: 365 | G40: =F40/F41 -> 24.892882 | H40: Trend is unfavorable | I40: In 2021 and 2022 stable and for 2023 unfavorable
A41: Cost of Goods Sold/Avg accounts payable | B41: ='Finl Stmts'!B69/(('Finl Stmts'!B23+'Finl Stmts'!D23)/2) -> 13.484585 | D41: ='Finl Stmts'!D69/(('Finl Stmts'!D23+'Finl Stmts'!F23)/2) -> 14.436886 | F41: ='Finl Stmts'!F69/'Finl Stmts'!F23 -> 14.662826
A42: Note: Assume the supplier’s credit policy is 30 days
A44: Operating Cycle (days): Average time to conduct the business cycle: from initial purchase of materials/products to collect cash from sales | J44: Overall the ratio trend for Boston Beer Company's operating cycle is stable. In 2021 the operating cycle was 53 days, meaning the company was marginally more efficient in turning its investments in inventory and receivables into cash. In 2022 and 2023 the company slightly increased their operating cycle to 54 days which still indicates consistency in the company's ability to convert inventory and receivables into cash. The slight increase in later years is concerning because if the trend were to continue this would raise concerns about the company's operational efficiency.
A45: Inventory Conversion Period + Receivables Collection Period | C45: =C31+C35 -> 53.878621 | E45: =E31+E35 -> 54.10641 | G45: =G31+G35 -> 52.963021 | H45: Trend is stable | I45: In 2021, 2022 and 2023 stable
A47: Cash Cycle (days): The average length of time cash is tied up in working capital: need to get a bank loan or have excess cash on hand to sustain business during this time | J47: Boston Beer Company's cash cycle ratio is overall favorable. In 2021 the cash cycle was 28 days and this suggests a relatively stable cash flow process. In 2022 the cash cycle of 29 days shows that the company took a slightly longer time to convert investments in working capital back into cash. This may indicate a temporary slowdown in cash turnover. In 2023, the cash cycle was 27 days, indicating that cash was tied up in working capital for a slightly shorter period compared to 2022 and 2021. This shows improved liquidity and cash flow management.
A48: Gross operating cycle - Payables deferral period (in days) | C48: =C45-C40 -> 26.810677 | E48: =E45-E40 -> 28.82395 | G48: =G45-G40 -> 28.070138 | H48: Trend is favorable | I48: In 2021 favorable, 2022 favorable and 2023 slightly unfavorable
A50: Fixed Asset Turnover Ratio : $$ of Sales generated by $1 of Fixed Assets: how efficiently are you using your Fixed Assets? | J50: Over all the fixed asset turnover ratio for Boston Beer Company was slightly unfavorable to stable. In 2023, the fixed asset turnover ratio was 3.07 indicating a slight decline in efficiency compared to 2022. This suggests that the company generated slightly less revenue per dollar of fixed assets due to decreased sales. In 2022, the ratio increased to 3.14, showing a slight improvement in asset utilization compared to 2021. This suggest the company was able to generate more revenue per dollar of fixed assets, reflecting better operational efficiency. In 2021, with at ratio of 3.10, the company had a solid level of asset utilization. Though it is slightly lower than 2022, it was relatively stable.
A51: Sales | B51: ='Finl Stmts'!B68 -> 2008625 | C51: =B51/B52 -> 3.0656249 | D51: ='Finl Stmts'!D68 -> 2090334 | E51: =D51/D52 -> 3.1369346 | F51: ='Finl Stmts'!F68 -> 2057622 | G51: =F51/F52 -> 3.0950294 | H51: Trend is slightly unfavorabe/stable | I51: In 2021 unfavorable, 2022 favorable and in 2023 unfavorable
A52: Avg Net fixed assets | B52: =('Finl Stmts'!B13+'Finl Stmts'!D13)/2 -> 655209 | D52: =('Finl Stmts'!D13+'Finl Stmts'!F13)/2 -> 666362 | F52: ='Finl Stmts'!F13 -> 664815
A54: Total assets turnover ratio: $$ of Sales generated by $1 of Total Assets: how efficiently are you using your Total Assets? | J54: The overall trend for Boston Beer Company's total asset turnover ratio is unfavorable because the ratios have declined from 1.49 in 2022 to 1.41 in 2023, indicating that the company is generating fewer sales per dollar of assets over time which is an indicator of lower sales. In 2021 the company utilized its assets efficiently maintaining a strong turnover rate and effectively turning its assets into revenue. In 2022, similar to 2021, the company continued to maintain efficiency with a ratio of 1.49. However in 2023, the company asset efficiency declined, meaning it generated fewer sales per dollar of assets compared to previous years which indicates increased asset base without proportional revenue growth.
A55: Sales | B55: ='Finl Stmts'!B68 -> 2008625 | C55: =B55/B56 -> 1.4091827 | D55: ='Finl Stmts'!D68 -> 2090334 | E55: =D55/D56 -> 1.4890768 | F55: ='Finl Stmts'!F68 -> 2057622 | G55: =F55/F56 -> 1.4837365 | H55: Trend is unfavorable | I55: In 2021, 2022 and 2023 unfavorable
A56: Avg Total assets | B56: =('Finl Stmts'!B20+'Finl Stmts'!D20)/2 -> 1425383 | D56: =('Finl Stmts'!D20+'Finl Stmts'!F20)/2 -> 1403778.5 | F56: ='Finl Stmts'!F20 -> 1386784
A58: Solvency: Debt Management Ratios (ability of business to meet it's long term obligations: depends on capital structure - how much use debt vs. equity - and degree of operating leverage)
B59: =$B$3 -> 2023 | D59: =$D$3 -> 2022 | F59: =$F$3 -> 2021
A60: Debt Ratio: measures the % of a firm's capital structure provided by creditors. Creditors prefer this to be low as a cushion against losses | J60: Boston Beer Company has been actively paying down debt while increasing its total invested capital, which is a favorable trend. This reduction in debt enhances financial stability, lowers financial risk, and improves creditworthiness, potentially making the company more attractive to investors. In 2021, the company had the highest debt ratio among the three years, meaning greater portion of its capital structure was financed through debt which means higher financial obligation. In 2022 the debt ratio decreased, showing that the company reduced its reliance on debt while increasing total invested capital. Which shows lower risk. In 2023, with the lowest debt ratio, the company significantly reduced its debt burden without taking on any new debt. This implied reduced interest expenses for the company but since sales were declining, I would not say that it helped with improved financial health or greater flexibility for future investment since much of the cash flow from operations came from inside the company and not operational efficiency.
A61: Total interest bearing debt | B61: ='Finl Stmts'!B28+'Finl Stmts'!B33 -> 45274 | C61: =B61/B62 -> 0.040307941 | D61: ='Finl Stmts'!D28+'Finl Stmts'!D33 -> 54140 | E61: =D61/D62 -> 0.048223506 | F61: ='Finl Stmts'!F28+'Finl Stmts'!F33 -> 61483 | G61: =F61/F62 -> 0.058841488 | H61: Trend is favorable | I61: In 2021 and 2022 favorable and in 2023 unfavorable
A62: Total Invested Capital: Int B Debt + All Equity | B62: =B61+'Finl Stmts'!B45 -> 1123203 | D62: =D61+'Finl Stmts'!D45 -> 1122689 | F62: =F61+'Finl Stmts'!F45 -> 1044892
A64: Times-interest-earned ratio(TIE): ability of business to pay it's annual interest expense
A65: Net Operating Earnings (Earnings Before Interest Taxes: EBIT) | B65: ='Finl Stmts'!B77 -> 100001 | C65: =B65/B66 -> 71.023438 | D65: ='Finl Stmts'!D77 -> 90791 | E65: =D65/D66 -> 47.385699 | F65: ='Finl Stmts'!F77 -> 7997 | G65: =F65/F66 -> 8.1768916 | H65: Trend is favorable | I65: In 2021 unfavorable, in 2022 and 2023 favorable | J65: Boston Beer Company's Times Interest Earned (TIE) ratio is favorable overall, with steady improvements each year, indicating a stronger ability to cover its annual interest obligations. In 2021 the company has a low EBIT and somewhat low interest rate expense resulting in a modest ability to cover interest payments. In 2022, EBIT increased significantly from 2021, while interest expense remained relatively low, greatly improving the company's capacity to cover interest payments. In 2023, EBIT continued to grow, but at a slower rate compared to the significant spike in 2022. Despite this, the interest expense was even lower than in 2022, further enhancing the company’s interest coverage. This trend indicates lower financial risk.
A66: Net Interest expense (enter as a + #) | B66: =-'Finl Stmts'!B80 -> 1408 | D66: =-'Finl Stmts'!D80 -> 1916 | F66: =-'Finl Stmts'!F80 -> 978
A68: Debt to Equity Ratio: reflects LT debt payment ability. Lower ratio means lower relative debt burden & less risk of not repaying creditors. Should not be larger than 2.0
A69: Total interest bearing debt | B69: =B61 -> 45274 | C69: =B69/B70 -> 0.042000911 | D69: =D61 -> 54140 | E69: =D69/D70 -> 0.050666839 | F69: =F61 -> 61483 | G69: =F69/F70 -> 0.062520274 | H69: Trend is favorable | I69: In 2021, 2022 and 2023 favorable | J69: Boston Beer Company's debt to equity ratio is very favorable overall, with steady improvements each year, indicating a stronger ability to cover its annual interest obligations. In 2021 the ratio was .06 which indicates the company had a lower relative debt ratio and could repay creditors. 2022 and 2023 both saw improvements in the ratio by .01. Indicating that the company was actively paying down debt each year.
A70: Total Equity | B70: ='Finl Stmts'!B45 -> 1077929 | D70: ='Finl Stmts'!D45 -> 1068549 | F70: ='Finl Stmts'!F45 -> 983409
A72: Debt to Total Assets Ratio: Indicates what % of assets are funded with liabilities versus equity
A73: Total Liabilities | B73: ='Finl Stmts'!B34 -> 352064 | C73: =B73/B74 -> 0.24619981 | D73: ='Finl Stmts'!D34 -> 352224 | E73: =D73/D74 -> 0.24791012 | F73: ='Finl Stmts'!F34 -> 403375 | G73: =F73/F74 -> 0.29087082 | H73: Trend is favorable | I73: In 2021, 2022 and 2023 favorable | J73: oston Beer Company's debt-to-total-assets ratio is overall favorable, with a steady decrease each year, indicating that a smaller percentage of assets is being funded by liabilities rather than equity. In 2021, the ratio was 29%, followed by a decline to 25% in both 2022 and 2023. However, while a lower debt ratio reduces financial risk, it is concerning in the context of declining sales. If the company continues to rely more on asset sales rather than strategic debt financing, it may limit growth opportunities or struggle to maintain operations efficiently. This trend should be closely monitored to ensure financial stability and long-term sustainability.
A74: Total Assets | B74: ='Finl Stmts'!B20 -> 1429993 | D74: ='Finl Stmts'!D20 -> 1420773 | F74: ='Finl Stmts'!F20 -> 1386784
A76: Cost Structure / Leverage
A77: Leverage: leverage is the relative amount of fixed costs in a firm's overall cost structure. Leverage creates risk because fixed costs must be paid, regardless of the level of sales.
A78: Operating Leverage: created from the use of high levels of plant and machinery in the production process, revealed through charges for depreciation, property taxes, etc.
A79: Degree of Operating Leverage (DOL): | H79: Trend is favoarable | I79: In 2022 unfavorable and in 2023 favorable | J79: Overall this trend is favorable due to the extreme leverage from 2022 which has normalized in 2023, reducing financial risk. However the drop in sales is a red flag, since just lower leverage alone does not compensate for revenue struggles. In 2022 the company had extremely high operating leverage, so small changes in sales caused massive fluctuations in EBIT. Causing extreme volatility and suggests a high proportion of fixed costs. While EBIT increased significantly this year, the high leverage indicates significant risk if sales were to decline. In 2023, the company’s operating leverage dropped dramatically, indicating a shift to lower fixed costs or better cost control. This makes EBIT less sensitive to sales fluctuations, which reduces financial risk but may also indicate lower growth potential. However, since sales declined for that year, this drop in leverage could be a protective adjustment.
A80: % change in Operating Income (EBIT) | B80: ='Finl Stmts'!I77 -> 0.10144177 | D80: ='Finl Stmts'!J77 -> 10.353132
A81: % change in Sales | B81: ='Finl Stmts'!I68 -> -0.039088969 | D81: ='Finl Stmts'!J68 -> 0.015897964
A83: Degree of Financial Leverage (DFL): | B83: Created from the use of high levels of debt financing, revealed through charges for interest expense (a fixed expense with bankruptcy risk for non-payment).
A84: % change in Net Income | B84: ='Finl Stmts'!I85 -> 0.13360986 | D84: ='Finl Stmts'!J85 -> 3.6219336 | H84: Trend is unfavorable | I84: In 2022 favorable and in 2023 unfavorable | J84: For Boston Beer Company 2022 shows and exceptional year with substantial growth, but when analyzing these gains we can see that it is not from core business operations so the gains are not substantial which is concerning. In 2023 the numbers suggest a slowdown, with less favorable operational performance which helps support that the exceptional gain in 2022 was not from core business operations. The trend overall shows some concerns due to sustainability but overall is a favorable trend.
A85: % change in EBIT | B85: ='Finl Stmts'!I77 -> 0.10144177 | D85: ='Finl Stmts'!J77 -> 10.353132
A87: Sales Analysis
B88: =$B$3 -> 2023 | D88: =$D$3 -> 2022 | F88: =$F$3 -> 2021
A89: Revenue per unit sold: (inventory companies) or per square foot | J89: The trend in revenue per unit sold shows a consistent increase over the past three years.This suggests that despite declining sales volume (from 8504 barrels in 2021 to 7678 barrels in 2023), Boston Beer Company has been able to achieve higher prices per barrel, likely due to product mix, pricing strategies, or premium product offerings. However, the decline in total sales volume signals a potential challenge in maintaining demand or market share, which could affect long-term growth if not addressed.
A90: Sales | B90: ='Finl Stmts'!B68 -> 2008625 | C90: 261.61 | D90: ='Finl Stmts'!D68 -> 2090334 | E90: =D90/D91 -> 255.44837 | F90: ='Finl Stmts'!F68 -> 2057622 | G90: =F90/F91 -> 241.95931 | H90: Trend is favorable | I90: In 2021, 2022 and 2023 favorable
A91: Units Sold (or total sq feet or # stores) Find an operating metric in 10-K | B91: 7678 | D91: 8183 | F91: 8504
A92: A/R growth to Sales growth Ratio: | J92: In 2023, Boston Beer Company's A/R Growth to Sales Growth Ratio was -4.66, meaning accounts receivable grew significantly by 18% while sales declined by 4%. This is an unfavorable trend as the company may be struggling with slower collections or extending more credit or loosening their credit terms to customers to drive sales that wouldn't otherwise happen which would of artificially inflated sales numbers in the short term, improving some financial results. In 2022, the A/R Growth to Sales Growth Ratio was 1.89, with accounts receivable increasing by 3% while sales grew by 2%. This represents a slightly unfavorable trend. While it is common for A/R to grow alongside sales, the higher growth in receivables compared to sales suggests that like 2023, the company may have extended more credit or loosened their credit terms to customers or faced slower collections. This trend should have been monitored closely to prevent further deterioration, like the ratio results of 2023.
A93: Accounts Receivable Growth vs. | B93: ='Finl Stmts'!I8 -> 0.18218874 | C93: =B93/B94 -> -4.6608734 | D93: ='Finl Stmts'!J8 -> 0.029988005 | E93: =D93/D94 -> 1.8862796 | H93: Trend is unfavorable | I93: In 2022 and 2023 unfavorable
A94: Sales Growth | B94: ='Finl Stmts'!I68 -> -0.039088969 | D94: ='Finl Stmts'!J68 -> 0.015897964
A96: Revenue per Employee:
A97: Sales | B97: =B90 -> 2008625 | C97: =B97/B98 -> 791.73236 | D97: =D90 -> 2090334 | E97: =D97/D98 -> 821.99528 | F97: =F90 -> 2057622 | G97: =F97/F98 -> 823.0488 | H97: Trend is unfavorable | I97: In 2021 and 2022 stable, in 2023 unfavorable | J97: Revenue per employee was stable between 2021 and 2022 with revenue per employee for the year around 82,200. This shows consistent efficiency despite a slight increase in total sales and employees. The small dip in revenue per employee, even though revenue increase and employees increased, means that the increase in employees might have slightly outpaced the growth in sales. In 2023, there was a drop in both revenue and employees, with employee revenue also dropping to 79,173 per employee. This suggests that the company may have been trying to cut costs by cutting employees and this could of resulted in less efficiency resulting in lower sales. Or the company knew sales were declining and cut employees to save more cash. Regardless, this is an unfavorable trend if it were to continue.
A98: # employees (search 10-K, company website or google) | B98: 2537 | D98: 2543 | F98: 2500
A100: Profitability Ratios
A101: Gross Profit Margin: (stable?) | B101: =$B$3 -> 2023 | D101: =$D$3 -> 2022 | F101: =$F$3 -> 2021 | J101: In 2021, Boston Beer Company's gross profit margin was 38.8%, which is relatively low compared to the following years. This indicates higher production costs or lower pricing power, which could reflect inefficiencies in cost management that suggests pressure on profitability. In 2022, the gross profit margin increased to 41.2%, reflecting improved cost control or slightly better pricing strategies. While the increase is a favorable trend, the company's sales remained relatively flat, indicating that the margin growth was likely due to internal efficiencies rather than revenue expansion. In 2023, the gross profit margin further improved to 42.4%, representing continued cost management efforts. However, with sales declining by approximately 4%, the margin improvement may have been partially driven by cost-cutting measures rather than pricing strength.
A102: Gross Profit | B102: ='Finl Stmts'!B70 -> 852369 | C102: =B102/B103 -> 0.42435447 | D102: ='Finl Stmts'!D70 -> 861986 | E102: =D102/D103 -> 0.41236759 | F102: ='Finl Stmts'!F70 -> 797792 | G102: =F102/F103 -> 0.38772525 | H102: Trend is favorable | I102: In 2021 unfavorable and in 2022 and 2023 favorable
A103: Sales | B103: ='Finl Stmts'!B68 -> 2008625 | D103: ='Finl Stmts'!D68 -> 2090334 | F103: ='Finl Stmts'!F68 -> 2057622
A105: Net Operating Profit:
A106: EBIT | B106: ='Finl Stmts'!B77 -> 100001 | C106: =B106/B107 -> 0.049785799 | D106: ='Finl Stmts'!D77 -> 90791 | E106: =D106/D107 -> 0.043433729 | F106: ='Finl Stmts'!F77 -> 7997 | G106: =F106/F107 -> 0.0038865253 | H106: Trend is favorable | I106: In 2021 unfavorable and in 2022 and 2023 favorable | J106: In 2021, Boston Beer Company's EBIT margin was 3.9%, indicating weak operating profitability. This low margin reflects limited profitability from core operations. In 2022, the EBIT margin improved to 4.3%, showing slight progress in operational efficiency. While this is a favorable trend, the modest increase indicates that the company was struggling to generate significant profits from its sales. In 2023, the EBIT margin further increased to 5.0%, reflecting continued improvements in operating efficiency and cost management. Despite the decline in sales, the company was able to enhance profitability, which is a favorable trend.
A107: Sales | B107: ='Finl Stmts'!B68 -> 2008625 | D107: ='Finl Stmts'!D68 -> 2090334 | F107: ='Finl Stmts'!F68 -> 2057622
A109: Profit margin / Return on Sales (ROS)
A110: Net Income | B110: ='Finl Stmts'!B85 -> 76250 | C110: =B110/B111 -> 0.037961292 | D110: ='Finl Stmts'!D85 -> 67263 | E110: =D110/D111 -> 0.032178111 | F110: ='Finl Stmts'!F85 -> 14553 | G110: =F110/F111 -> 0.0070727276 | H110: Trend is favorable | I110: In 2021 unfavorable and in 2022 and 2023 favorable | J110: In 2021, Boston Beer Company had a profit margin of 0.7%, indicating minimal profitability. This extremely low margin suggests shows that the company struggled to convert sales into profit. In 2022, the profit margin improved to 3.2%, reflecting an increased operational efficiency but the margin remains relatively low, suggesting the company still faced profitability challenges despite the slight increase in net income. In 2023, the profit margin rose further to 3.8%, continuing the positive trajectory. The company's ability to grow its net income despite declining sales suggests improved expense management. Even though this is a favorable trend, the company still needs to focus on boosting sales to further strengthen profitability.
A111: Sales | B111: ='Finl Stmts'!B68 -> 2008625 | D111: ='Finl Stmts'!D68 -> 2090334 | F111: ='Finl Stmts'!F68 -> 2057622
A113: Basic Earning Power (BEP): Earning power of the firm’s assets before the influences of taxes and debt
A114: Operating Income (EBIT) | B114: ='Finl Stmts'!B77 -> 100001 | C114: =B114/B115 -> 0.069931112 | D114: ='Finl Stmts'!D77 -> 90791 | E114: =D114/D115 -> 0.063902538 | F114: ='Finl Stmts'!F77 -> 7997 | G114: =F114/F115 -> 0.0057665794 | H114: Trend is favorable | I114: In 2021 unfavorable, 2022 and 2023 favorable | J114: In 2021, Boston Beer Company’s Basic Earning Power was 0.6%, indicating extremely low efficiency in using its assets to generate operating income. Suggesting the company struggled to turn its asset base into profits. In 2022, the Basic Earning Power improved to 6.4%, reflecting a significant recovery in operational efficiency. This increase suggests the company made progress in managing expenses and utilizing its assets more effectively. In 2023, the Basic Earning Power increased further to 7.0% and even though it was only a slight increase and not nearly as large of an increase from 2021 to 2022, it still demonstrated continued improvements in asset utilization and operational efficiency. However, maintaining this progress will require a focus on reversing the sales decline to sustain profitability.
A115: Total Assets | B115: ='Finl Stmts'!B20 -> 1429993 | D115: ='Finl Stmts'!D20 -> 1420773 | F115: ='Finl Stmts'!F20 -> 1386784
A117: Return on Total Assets (ROA): | J117: Boston Beer Company’s ROA in 2021 was 1.0%, indicating poor efficiency in using its assets to generate net income. This low return suggests operational challenges and limited profitability. Indicating the company struggled to achieve strong returns from its asset base. In the following year, 2022, the ROA improved to 4.8%, reflecting better asset utilization and stronger profitability. However the return still remains relatively low, suggesting that further improvements in operational efficiency and revenue growth are necessary. The ROA increased further in 2023, to 5.3%, indicating continued progress in generating returns from the company's assets. However, with sales declining, sustaining this growth may become challenging without efforts to boost revenue.
A118: Net Income | B118: ='Finl Stmts'!B85 -> 76250 | C118: =B118/B119 -> 0.053494394 | D118: ='Finl Stmts'!D85 -> 67263 | E118: =D118/D119 -> 0.047915679 | F118: ='Finl Stmts'!F85 -> 14553 | G118: =F118/F119 -> 0.010494064 | H118: Trend is favorable | I118: In 2021 unfavorable and in 2022 amd 2023 favorable
A119: Avg Total assets | B119: =('Finl Stmts'!B20+'Finl Stmts'!D20)/2 -> 1425383 | D119: =('Finl Stmts'!D20+'Finl Stmts'!F20)/2 -> 1403778.5 | F119: =('Finl Stmts'!F20) -> 1386784
A121: Return on common Equity (ROE):
A122: Net Income - Preferred Dividends | B122: ='Finl Stmts'!B85-'Finl Stmts'!B146 -> 76250 | C122: =B122/B123 -> 0.071046617 | D122: ='Finl Stmts'!D85-'Finl Stmts'!D146 -> 67263 | E122: =D122/D123 -> 0.065559821 | F122: ='Finl Stmts'!F85-'Finl Stmts'!F146 -> 14553 | G122: =F122/F123 -> 0.014798522 | H122: Trend is favorable | I122: 2021 unfavorable, 2022-2023 favorable | J122: Boston Beer Company’s ROE in 2021 was 1.5%, indicating that the company generated a very low return for its common shareholders. This poor performance suggests inefficient use of equity capital and low profitability. In 2022, the ROE improved to 6.6%, reflecting better profitability and more effective use of shareholders' equity. However, the return remains relatively low compared to market expectations, indicating room for further improvement. The ROE in 2023 increased further to 7.1%, signaling continued improvement in profitability and efficient use of equity. However, the declining sales and reliance on cost-cutting measures suggest that sustaining this level of return may become challenging without renewed revenue growth. During all three years, Boston Beer Company did not pay any dividends. The lack of dividends highlights that the ROE improvements are primarily a result of internal reinvestment rather than distributing earnings to shareholders. Which is not necessarily negative, but it does increase pressure on management to show that these retained earnings are driving long-term value.
A123: Avg Common Shareholder's Equity | B123: =('Finl Stmts'!B44+'Finl Stmts'!D44)/2 -> 1073239 | D123: =('Finl Stmts'!D44+'Finl Stmts'!F44)/2 -> 1025979 | F123: =('Finl Stmts'!F44) -> 983409
A125: Return on Invested Capital: Total Return for company investors | H125: Trend is favorable | I125: In 2021 unfavorable and in 2022 amd 2023 favorable | J125: In 2021, Boston Beer Company’s ROIC was 5.7%, indicating a relatively low return for investors given the capital invested in the company. This suggests the company faced challenges in generating sufficient returns from its operations. In 2022, the ROIC increased to 6.0%, reflecting improved operational efficiency and better management of capital. However, the modest improvement suggests there was still room for enhanced profitability. In 2023, the ROIC rose further to 6.6%, indicating continued progress in generating returns on the capital invested by both shareholders and debtholders. This improved ratio with declining sales causes some concern that sustaining this level of return may become challenging without future revenue growth.
A126: NOPAT (=EBIT*(1-T)) | B126: ='Add''l Calc'!C10 -> 74000.74 | C126: =B126/B127 -> 0.065883674 | D126: ='Add''l Calc'!E10 -> 67185.34 | E126: =D126/D127 -> 0.059843234 | F126: ='Add''l Calc'!G10 -> 5917.78 | G126: =F126/F127 -> 0.0056635327
A127: Total Invested Capital (= Int bearing debt + Eq) | B127: =B62 -> 1123203 | D127: =D62 -> 1122689 | F127: =F62 -> 1044892
...

Sheet Add'l Calc
B2: Boston Beer Company
B3: Laura Dampman
A4: Phase I: Additional Calculations & Analysis
B5: See Step 8 Instructions for Questions to Answer | I5: Analysis: Trend? What does it indicate?
A6: Step 8: | C6: ='Finl Stmts'!B4 -> 2023 | E6: ='Finl Stmts'!D4 -> 2022 | G6: ='Finl Stmts'!F4 -> 2021
C7: Popular measure of Free Cash Flow from operations before considering impacts of debt, taxes and future growth needs.
A8: a1 | B8: EBITDA: (EBIT + Depreciation + Amortization) is a quick and dirty measure of cash generated by operations | C8: ='Finl Stmts'!B77+'Finl Stmts'!B95 -> 188142 | E8: ='Finl Stmts'!D77+'Finl Stmts'!D95 -> 172147 | G8: ='Finl Stmts'!F77+'Finl Stmts'!F95 -> 80093 | I8: EBITDA Growth is a positive indicator of operational profitability, but it's crucial to recognize that the extraordinary growth in 2022 might have been driven by one-time gains or cost cuts rather than ongoing improvements in core operations. The slower growth in 2023, combined with declining revenues and increasing liabilities, suggests that this growth might not be sustainable. With operational cash flows not being able to cover current liabilities in 2021 and 2022 could signal potential financial stress that could hinder long term stability.
A10: b | B10: NOPAT: (EBIT*(1-T)). Use T from tax analysis below | C10: ='Finl Stmts'!B77*C19 -> 74000.74 | E10: ='Finl Stmts'!D77*E19 -> 67185.34 | G10: ='Finl Stmts'!F77*G19 -> 5917.78 | I10: NOPAT shows that after-tax operating performance is improving, but again, the sharp increase in 2022 could have been driven by temporary factors like tax benefits or non-operating gains. The declining operational metrics, such as decreased sales and impairments, point to potential weaknesses in maintaining these profit levels.
I11: The increase in working capital from 2021 to 2023 suggests that Boston Beer Company is strengthening its liquidity position, which is generally a positive sign for its ability to meet short-term obligations and finance day-to-day operations. However, the significant growth in working capital, especially in 2022, raises questions about the efficiency of how current assets are being managed, particularly in areas like accounts receivable and inventory. If the increase in working capital is largely driven by uncollected receivables or unsold inventory, it could signal potential operational inefficiencies that need to be addressed. While the overall trend is positive, it will be important for the company to ensure that these increased reserves are being used effectively to drive growth and profitability rather than simply accumulating without turning it into profitable returns.
A12: c 1. | B12: Working Capital (WC): = CA - CL | C12: ='Finl Stmts'!B11-'Finl Stmts'!B29 -> 280222 | E12: ='Finl Stmts'!D11-'Finl Stmts'!D29 -> 219002 | G12: ='Finl Stmts'!F11-'Finl Stmts'!F29 -> 90235
B13: Net Working Capital Ratio: (CA - CL) / Total Assets
A14: d | B14: Free Cash Flow (Modified): (NOPAT+ Depreciation & Amortization) - (CapEx) Note: if FCF is negative, then company needs to raise new money in capital markets to invest in CapX | C14: =C10+'Finl Stmts'!B95+'Finl Stmts'!B118 -> 98054.74 | E14: =E10+'Finl Stmts'!D95+'Finl Stmts'!D118 -> 57959.34 | G14: =G10+'Finl Stmts'!F95+'Finl Stmts'!F118 -> -69905.22 | I14: While the increase in free cash flow is a positive sign, the underlying factors—declining sales, growing accounts receivable, increasing accounts payable, and negative investing cash flows—indicate that the company may not be improving its operational efficiency. Instead, it appears to be generating cash through internal liquidity management (such as using working capital adjustments, reducing debt, and potentially cashing in short-term investments). This reliance on financial maneuvers to generate cash is not sustainable in the long term. If the company continues to see declining sales and operational inefficiencies (increased receivables), it could face liquidity challenges in the future. The company needs to focus on improving its core business operations and reducing reliance on these internal cash-generation strategies to ensure long-term financial health and sustainability.
B15: Note: Source of CapEx = Stmt of Cash flows Investing section: Purchases of Property & Equipment + Purchases of Intangible assets (do not include one time purchases of a business and do not include goodwill). Be careful because this is shown as a negative number. Watch the parenthesis. It should reduce NOPAT
A17: e | B17: Effective Tax Rate: Tax Expense/Earnings Before Taxes (EBT): (compute for each year) | C17: ='Finl Stmts'!B84/'Finl Stmts'!B83 -> 0.30421214 | E17: ='Finl Stmts'!D84/'Finl Stmts'!D83 -> 0.26437071 | G17: ='Finl Stmts'!F84/'Finl Stmts'!F83 -> -1.106383 | I17: Boston Beer Company's effective tax rate trend is unfavorable. It shows an increase in the effective tax rate from 2021 to 2023, from a negative tax rate in 2021 to a 30% rate in 2023. The only year that the effective tax rate did not come close to the effective tax rate was in 2021, with an effecitve tax rate of -111% which the sharp negative rate was likely driven by tax benefits from losses, impairments, or adjustments in deferred tax assets noted in financial statements. The trend from 2021 (a tax benefit) to 2023 (a higher-than-nominal tax rate) is unfavorable as it suggests that the company is facing higher tax expenses, which could reduce future profitability if the trend continues.
B18: Nominal Tax Rate (T) (statutory 21%+4% state + 1% local) | C18: =0.21+0.04+0.01 -> 0.26 | E18: =0.21+0.04+0.01 -> 0.26 | G18: =0.21+0.04+0.01 -> 0.26
B19: After Tax Impact (1-T) (what company keeps) | C19: =1-C18 -> 0.74 | E19: =1-E18 -> 0.74 | G19: =1-G18 -> 0.74
A21: f | B21: Sources of Funding for Total Assets: | C21: Book Value $$ | E21: % | I21: The 2023 reduction in free liabilities from operations is generally a favorable trend since it reflects a more balanced and sustainable approach. However, maintaining some level of operational liabilities is normal and can be beneficial for cash flow management. The company should ensure that further reductions do not harm operational efficiency or supplier relationships.
A22: 1) | B22: Vendor/Supplier/Govt/EE Funding: (Free liabilities from Operations) | C22: ='Finl Stmts'!B34-'Finl Stmts'!B33-'Finl Stmts'!B28 -> 306790 | E22: ='Finl Stmts'!D34-'Finl Stmts'!D33-'Finl Stmts'!D28 -> 298084 | G22: ='Finl Stmts'!F34-'Finl Stmts'!F33-'Finl Stmts'!F28 -> 341892
A24: 2) | B24: Debt Investor Funding: (Interest bearing): | C24: ='Finl Stmts'!B28+'Finl Stmts'!B33 -> 45274 | E24: ='Finl Stmts'!D28+'Finl Stmts'!D33 -> 54140 | G24: ='Finl Stmts'!F28+'Finl Stmts'!F33 -> 61483 | I24: The decrease in debt from 2021 to 2023 is a favorable trend as it suggests that Boston Beer Company is reducing financial risk and strengthening its balance sheet. However, maintaining a manageable level of debt can be beneficial for leveraging growth opportunities, so the company should ensure it has a balanced structure moving forward.
A26: 3) | B26: Equity Investor Funding: $$ + %:
B27: Common Equity | C27: ='Finl Stmts'!B44 -> 1077929 | E27: ='Finl Stmts'!D44 -> 1068549 | G27: ='Finl Stmts'!F44 -> 983409 | I27: The trend in equity investor funding is favorable as Boston Beer Company has consistently increased its equity base. This growth suggests financial resilience and strengthens the company's capital structure. Maintaining a high equity-to-assets ratio reduces financial risk and provides flexibility, reflecting a cautious approach to funding rather than relying heavily on external borrowing.
B28: Preferred Equity | C28: ='Finl Stmts'!B37 -> 0 | E28: ='Finl Stmts'!D37 -> 0 | G28: ='Finl Stmts'!F37 -> 0
B29: Noncontrolling Interest | C29: ='Finl Stmts'!B36 -> 0 | E29: ='Finl Stmts'!D36 -> 0 | G29: ='Finl Stmts'!F36 -> 0
B30: SubTotal Total Assets | C30: =SUM(C22:C29) -> 1429993 | E30: =SUM(E22:E29) -> 1420773 | G30: =SUM(G22:G29) -> 1386784
B31: Total Assets per Balance Sheet | C31: ='Finl Stmts'!B20 -> 1429993 | E31: ='Finl Stmts'!D20 -> 1420773 | G31: ='Finl Stmts'!F20 -> 1386784
B32: Difference (should = 0) | C32: =C30-C31 -> 0 | E32: =E30-E31 -> 0 | G32: =G30-G31 -> 0
A34: g | B34: All Interest Bearing Debt/ EBITDA. Minimum # years for company to pay off debt IF it paid no taxes, interest expense, pmts to shareholders or made investments. | C34: =C22/C8 -> 1.6306301 | E34: =E22/E8 -> 1.7315666 | I34: The 2-year Debt/EBITDA ratio in both 2023 and 2022 is a favorable trend, indicating the company is maintaining a strong ability to service its debt. This is a favorable trend.
A36: h | B36: What story is the data telling? List a MINIMUM of 2 things the company doing well . | C36: Areas that Boston Beer Company has done well in are effective cash generation and cost cutting measures, debt management, maintaining a stable share count and increasing EPS. Boston Beer Company has done well in implementing cost-cutting measures and generating cash through asset liquidation. By reducing operating expenses and strategically liquidating short-term assets, the company was able to increase net income despite declining sales. In 2022, Boston Beer Company's net income surged by 362%, and in 2023, it grew another 13%, largely due to cost-cutting efforts and asset sales. This also led to a 572% increase in cash and cash equivalents in 2022 and another 65% increase in 2023, further strengthening the company’s liquidity position. The company also paid down 13% of its long-term debt in 2022 and maintained that level in 2023, reducing financial risk. While cost-cutting and asset liquidation are not sustainable long-term solutions, it helped stabilize the company’s financials and provided flexibility for future reinvestment. Moving forward, Boston Beer must shift from cutting costs to driving revenue growth to sustain profitability. Boston Beer Company has also been able to maintain a stable share count and increasing EPS. Despite financial challenges, Boston Beer Company has kept the number of outstanding shares stable. This means that its earnings per share (EPS) growth was driven by actual net income growth rather than artificial stock buybacks. In 2022, net income grew by 362%, leading to a sharp increase in EPS and then the net income rose again in 2023 by 13%. This stability in share count benefits long-term investors because it ensures EPS growth is not artificially inflated by reducing the number of shares. However, to maintain investor confidence, Boston Beer must now focus on driving revenue growth rather than relying on cost-cutting or asset liquidations. While Boston Beer Company has taken steps to strengthen its balance sheet and ensure liquidity, the combination of declining sales, asset liquidation, and a lack of growth investments, that I will be mentioning in the next section, raises concerns about the company's long-term growth prospects. Boston Beer Company's conservative financial approach may mitigate short-term risks, but without revenue growth and operational improvements, the company could face stagnation or further financial pressure in the future.
B37: List a MINIMUM of 3 areas the company needs to improve to help their financial performance | C37: Boston Beer Company's financial statements reveal that they have taken a conservative financial approch to help mitigate short term risks. There are several concerning trends, highlighting areas where the company must improve to achieve sustainable financial growth. One critical area for improvement is marketable securities and short-term investments. In 2022, Boston Beer Company completely liquidated all of its marketable securities and investments, likely due to the need for an influx of cash. This decision followed two consecutive years (2021 and 2022) where operating cash flows were negative, meaning the company did not generate enough money from its core business to cover its current liabilities. The problem is that this trend continued into 2023, with marketable securities and investments still at 0%. By failing to reinvest cash into short-term securities, the company now lacks easily accessible liquid assets, which can make cash flow management more difficult. Additionally, Boston Beer is missing out on potential returns that it could have earned through interest or capital appreciation. Holding excess cash may seem like a prudent approach, but without reinvesting, it becomes an inefficient use of capital. Investors could interpret this as a lack of strategic planning or growth opportunities, which may negatively affect market confidence and the company’s ability to secure favorable financing in the future. To improve, Boston Beer Company should develop a balanced approach between maintaining liquidity and reinvesting cash into short-term securities or other high-return opportunities. Another major area of concern is fluctuating sales and weakening investor confidence. Boston Beer Company's sales grew by only 2% from 2021 to 2022 but then declined by 4% from 2022 to 2023. Despite an increasing EPS, the company’s stock price has been falling significantly, signaling investor concerns about future growth. The company's P/E ratio declined sharply from 426.21 in 2021 to 38.78 in 2023, suggesting investors initially overvalued the company but later adjusted their expectations as growth slowed. As well as the price-to-sales ratio decreasing each year, further indicating weak investor sentiment. Compounding this issue, Boston Beer Company did not pay dividends in any of the three years, despite a sharp increase in cash and cash equivalents (572% in 2022 and 65% in 2023). This suggests the company was holding onto cash instead of reinvesting or rewarding shareholders, making it less attractive to investors. While retaining cash can be a strategic move, Boston Beer has not used these funds effectively for reinvestment. Instead of relying on cost-cutting measures that artificially boost net income, the company should focus on increasing sales and operational efficiency to drive sustainable long-term profit growth. Additionally, the company’s negative financing cash flows in 2021 and 2023 indicate that it was paying off debt rather than securing new financing. While reducing debt can be a positive move, this strategy must be balanced with investments in future growth. The lack of both dividends and reinvestment efforts suggests that Boston Beer is failing to provide sufficient value to shareholders, which could lead to further stock price declines and reduced investor interest. In addition to declining sales, Boston Beer Company's accounts receivable (A/R) has increased significantly, rising by 3% in 2022 and then another 18% in 2023. Normally, A/R growth should align with rising sales, but Boston Beer’s sales actually declined in 2023. This mismatch suggests that the company is not efficiently collecting payments from customers, which could lead to future cash flow issues. One possible explanation is that Boston Beer loosened its credit terms to boost sales following weaker results in 2021. While this can be an effective short-term strategy, it carries risks like a higher A/R means more money is tied up in unpaid invoices, reducing available cash. Failure to collect payments on time increases the likelihood of bad debt, which can reduce net income and investors may see rising A/R as a warning sign that the company is struggling to manage its cash flow. To address this issue, Boston Beer Company should tighten its credit policies and improve collection efforts. This includes better monitoring of outstanding receivables, enforcing stricter payment deadlines, and evaluating customer creditworthiness more carefully. Without these changes, the company risks higher bad debt expenses and further financial instability.
